<?xml version="1.0" encoding="utf-8"?>
<xbrl
  xmlns="http://www.xbrl.org/2003/instance"
  xmlns:example="http://xyz.abc/IncomeStatementExample"
  xmlns:iso4217="http://www.xbrl.org/2003/iso4217"
  xmlns:link="http://www.xbrl.org/2003/linkbase"
  xmlns:xbrldi="http://xbrl.org/2006/xbrldi"
  xmlns:xlink="http://www.w3.org/1999/xlink">
    <link:schemaRef xlink:href="is.xsd" xlink:type="simple"/>
    <context id="c-01">
        <entity>
            <identifier scheme="http://www.any.gov/identifier">Example-IS</identifier>
            <segment>
                <xbrldi:explicitMember dimension="example:ProductServiceAxis">example:ProductMember</xbrldi:explicitMember>
            </segment>
        </entity>
        <period>
            <startDate>2020-01-01</startDate>
            <endDate>2020-06-30</endDate>
        </period>
    </context>
    <context id="c-02">
        <entity>
            <identifier scheme="http://www.any.gov/identifier">Example-IS</identifier>
            <segment>
                <xbrldi:explicitMember dimension="example:ProductServiceAxis">example:ServiceMember</xbrldi:explicitMember>
            </segment>
        </entity>
        <period>
            <startDate>2020-01-01</startDate>
            <endDate>2020-06-30</endDate>
        </period>
    </context>
    <context id="c-03">
        <entity>
            <identifier scheme="http://www.any.gov/identifier">Example-IS</identifier>
        </entity>
        <period>
            <startDate>2020-01-01</startDate>
            <endDate>2020-06-30</endDate>
        </period>
    </context>
    <unit id="u-01">
        <measure>iso4217:EGP</measure>
    </unit>
    <unit id="u-02">
        <measure>shares</measure>
    </unit>
    <unit id="u-03">
        <measure>pure</measure>
    </unit>
    <example:RevenueConcept contextRef="c-01" decimals="2" unitRef="u-01">5000</example:RevenueConcept>
    <example:RevenueConcept contextRef="c-02" decimals="2" unitRef="u-01">4000</example:RevenueConcept>
    <example:RevenueConcept contextRef="c-03" decimals="2" unitRef="u-01">9000</example:RevenueConcept>
    <example:CostOfRevenueConcept contextRef="c-01" decimals="2" unitRef="u-01">2000</example:CostOfRevenueConcept>
    <example:CostOfRevenueConcept contextRef="c-02" decimals="2" unitRef="u-01">1500</example:CostOfRevenueConcept>
    <example:CostOfRevenueConcept contextRef="c-03" decimals="2" unitRef="u-01">3500</example:CostOfRevenueConcept>
    <example:GrossProfitConcept contextRef="c-01" decimals="2" unitRef="u-01">3000</example:GrossProfitConcept>
    <example:GrossProfitConcept contextRef="c-02" decimals="2" unitRef="u-01">2500</example:GrossProfitConcept>
    <example:GrossProfitConcept contextRef="c-03" decimals="2" unitRef="u-01">5500</example:GrossProfitConcept>
    <example:ExpensesConcept contextRef="c-01" decimals="2" unitRef="u-01">1000</example:ExpensesConcept>
    <example:ExpensesConcept contextRef="c-02" decimals="2" unitRef="u-01">600</example:ExpensesConcept>
    <example:ExpensesConcept contextRef="c-03" decimals="2" unitRef="u-01">1600</example:ExpensesConcept>
    <example:NetProfitConcept contextRef="c-01" decimals="2" unitRef="u-01">2000</example:NetProfitConcept>
    <example:NetProfitConcept contextRef="c-02" decimals="2" unitRef="u-01">1900</example:NetProfitConcept>
    <example:NetProfitConcept contextRef="c-03" decimals="2" unitRef="u-01">4900</example:NetProfitConcept>
    <example:SharesOutstandingConcept contextRef="c-03" decimals="0" unitRef="u-02">1000</example:SharesOutstandingConcept>
    <example:EarningPerShareConcept contextRef="c-03" decimals="2" unitRef="u-03">4.90</example:EarningPerShareConcept>
</xbrl>
